wish_knowledge/__init__.py
wish_knowledge/config.py
wish_knowledge/exceptions.py
wish_knowledge/manager.py
wish_knowledge/py.typed
wish_knowledge/rag.py
wish_knowledge/sources.py
wish_knowledge/splitter.py
wish_knowledge/storage.py
wish_knowledge/vectorstore.py
wish_knowledge-0.7.0.dist-info/METADATA
wish_knowledge-0.7.0.dist-info/WHEEL
wish_knowledge-0.7.0.dist-info/RECORD
